{
    "updateDate": "2022/06/29",
    "Adb":"date",
    "appList": [
        {
            "packageName": "InstaShare 2 Host",
            "connections": {
                "UrlList": [
                    {   "type":"https",
                        "port":"443",
                        "url": "https://instashare2.benq.com"  
                    },
                    {   "type":"tcp",
                        "port":"5000",
                        "url": "none"
                    },
                    {   "type":"tcp",
                        "port":"6788",
                        "url": "none"
                    },
                    {   "type":"tcp",
                        "port":"6789",
                        "url": "none"
                    },
                    {   "type":"tcp",
                        "port":"7000",
                        "url": "none"
                    },
                    {   "type":"tcp",
                        "port":"7250",
                        "url": "none"
                    },
                    {   "type":"tcp",
                        "port":"7236",
                        "url": "none"
                    },
                    {   "type":"tcp",
                        "port":"8080",
                        "url": "none"
                    },
                    {   "type":"tcp",
                        "port":"8888",
                        "url": "none"
                    },
                    {   "type":"tcp",
                        "port":"50000",
                        "url": "none"
                    },
                    {   "type":"udp",
                        "port":"7002-7021",
                        "url": "none"
                    },
                    {   "type":"udp",
                        "port":"20002",
                        "url": "none"
                    },
                    {   "type":"udp",
                        "port":"65525-65535",
                        "url": "none"
                    }       
                ],
                "description": "Check your network status and press 'APP LOG' from sidebar, then click 'Cloud Feedback'."
            }
        },
        {
            "packageName": "InstaShare",
            "connections": {
                "UrlList": [
                    {   "type":"https",
                        "port":"443",
                        "url": "https://instashare2.benq.com"  
                    },
                    {   "type":"tcp",
                        "port":"8000",
                        "url": "none"
                    },
                    {   "type":"tcp",
                        "port":"8008",
                        "url": "none"
                    },
                    {   "type":"tcp",
                        "port":"8009",
                        "url": "none"
                    },
                    {   "type":"tcp",
                        "port":"8121",
                        "url": "none"
                    },
                    {   "type":"tcp",
                        "port":"25123",
                        "url": "none"
                    },
                    {   "type":"tcp",
                        "port":"51010",
                        "url": "none"
                    },
                    {   "type":"tcp",
                        "port":"51020",
                        "url": "none"
                    },
                    {   "type":"tcp",
                        "port":"51030",
                        "url": "none"
                    },
                    {   "type":"tcp",
                        "port":"51040",
                        "url": "none"
                    },
                    {   "type":"tcp",
                        "port":"52020",
                        "url": "none"
                    },
                    {   "type":"tcp",
                        "port":"52030",
                        "url": "none"
                    },
                    {   "type":"tcp",
                        "port":"56789",
                        "url": "none"
                    },
                    {   "type":"udp",
                        "port":"5353",
                        "url": "none"
                    },
                    {   "type":"udp",
                        "port":"25123",
                        "url": "none"
                    },
                    {   "type":"udp",
                        "port":"48689",
                        "url": "none"
                    }           
                ],
                "description": "Check your network status and press 'APP LOG' from sidebar, then click 'Cloud Feedback'."
            }
        }
    ]
}